{"total":16,"pageSize":10,"pageCount":2,"data":[{"title":"lambda calculus:Introduction","slug":"/lambda-calculus-introduction","date":"2017-03-12T07:31:30.000Z","updated":"2017-03-12T08:07:54.090Z","comments":true,"path":"api/articles//lambda-calculus-introduction.json","excerpt":null,"keywords":null,"content":null,"raw":null,"categories":[{"name":"函数式编程","path":"api/categories/函数式编程.json"}],"tags":[{"name":"lambda calculus","path":"api/tags/lambda calculus.json"}]},{"title":"加密算法简介","slug":"/salted-password-hashing","date":"2017-03-05T11:25:50.000Z","updated":"2017-03-05T13:26:49.801Z","comments":true,"path":"api/articles//salted-password-hashing.json","excerpt":null,"keywords":null,"content":null,"raw":null,"categories":[{"name":"algorithm","path":"api/categories/algorithm.json"}],"tags":[{"name":"网络安全","path":"api/tags/网络安全.json"},{"name":"加密算法","path":"api/tags/加密算法.json"}]},{"title":"Bash小技巧","slug":"/bash-shortcuts","date":"2017-02-11T15:07:28.000Z","updated":"2017-02-13T09:10:45.218Z","comments":true,"path":"api/articles//bash-shortcuts.json","excerpt":null,"keywords":null,"content":null,"raw":null,"categories":[{"name":"永远记不住的编程姿势","path":"api/categories/永远记不住的编程姿势.json"}],"tags":[{"name":"编程技巧","path":"api/tags/编程技巧.json"}]},{"title":"正则表达式：零宽断言(lookaround)","slug":"/regular-expression-lookahead-lookbehind","date":"2017-01-03T15:16:58.000Z","updated":"2017-02-13T09:09:10.339Z","comments":true,"path":"api/articles//regular-expression-lookahead-lookbehind.json","excerpt":null,"keywords":null,"content":null,"raw":null,"categories":[{"name":"永远记不住的编程姿势","path":"api/categories/永远记不住的编程姿势.json"}],"tags":[{"name":"编程技巧","path":"api/tags/编程技巧.json"}]},{"title":"Jackson序列化双向关联映射的四种方法","slug":"/jackson-serialize-bi-directional-relationship-infinite-recursion","date":"2017-01-01T06:07:03.000Z","updated":"2017-01-09T17:50:20.591Z","comments":true,"path":"api/articles//jackson-serialize-bi-directional-relationship-infinite-recursion.json","excerpt":null,"keywords":null,"content":null,"raw":null,"categories":[{"name":"java","path":"api/categories/java.json"}],"tags":[{"name":"jpa","path":"api/tags/jpa.json"},{"name":"hibernate","path":"api/tags/hibernate.json"},{"name":"spring mvc","path":"api/tags/spring mvc.json"},{"name":"jackson","path":"api/tags/jackson.json"}]},{"title":"Initial Setup Ubuntu16.04 server","slug":"/initial-setup-Ubuntu-16.04-server","date":"2016-12-04T03:44:13.000Z","updated":"2017-01-09T17:44:10.241Z","comments":true,"path":"api/articles//initial-setup-Ubuntu-16.04-server.json","excerpt":null,"keywords":null,"content":null,"raw":null,"categories":[{"name":"linux","path":"api/categories/linux.json"}],"tags":[{"name":"ubuntu","path":"api/tags/ubuntu.json"}]},{"title":"魔力数字与快速平方根倒数算法","slug":"/the-famous-magic-number-fast-inverse-square-root-algorithm","date":"2016-09-20T02:53:33.000Z","updated":"2017-01-09T17:50:20.595Z","comments":true,"path":"api/articles//the-famous-magic-number-fast-inverse-square-root-algorithm.json","excerpt":null,"keywords":null,"content":null,"raw":null,"categories":[{"name":"algorithm","path":"api/categories/algorithm.json"}],"tags":[{"name":"闲话算法","path":"api/tags/闲话算法.json"}]},{"title":"数值运算与牛顿迭代法","slug":"/integer-arithmetic-karatsuba-multiplication","date":"2016-06-04T08:12:23.000Z","updated":"2017-01-09T17:40:15.954Z","comments":true,"path":"api/articles//integer-arithmetic-karatsuba-multiplication.json","excerpt":null,"keywords":null,"content":null,"raw":null,"categories":[{"name":"algorithm","path":"api/categories/algorithm.json"}],"tags":[{"name":"闲话算法","path":"api/tags/闲话算法.json"}]},{"title":"香农信息论与回答老鼠喝药问题的正确姿势","slug":"/shannon-mathematical-theory-of-communication","date":"2016-05-22T05:50:35.000Z","updated":"2017-01-09T17:34:55.620Z","comments":true,"path":"api/articles//shannon-mathematical-theory-of-communication.json","excerpt":null,"keywords":null,"content":null,"raw":null,"categories":[{"name":"algorithm","path":"api/categories/algorithm.json"}],"tags":[{"name":"闲话算法","path":"api/tags/闲话算法.json"}]},{"title":"CSS清除浮动的原理与最佳实践","slug":"/css-float-clearfix-best-in-practice","date":"2016-05-20T07:26:52.000Z","updated":"2017-01-09T17:26:22.348Z","comments":true,"path":"api/articles//css-float-clearfix-best-in-practice.json","excerpt":null,"keywords":null,"content":null,"raw":null,"categories":[{"name":"css","path":"api/categories/css.json"}],"tags":[{"name":"fontend","path":"api/tags/fontend.json"}]}]}